{
  "updated_at": "2026-05-12T15:39:22.319920+00:00",
  "top_trending": {
    "ticker": "QUBT",
    "name": "Quantum Computing Inc.",
    "sentiment_delta": 0.0,
    "current_sentiment": 0.0,
    "sentiment_label": "Neutral",
    "bullish_pct": null,
    "tweet_volume": 252640,
    "price": 11.82,
    "change_pct": "+16.11%",
    "key_topics": [
      "Momentum",
      "Volume Spike"
    ]
  },
  "trending_list": [
    {
      "ticker": "BZFD",
      "name": "BuzzFeed, Inc.",
      "sentiment_delta": 0.0,
      "current_sentiment": 0.0,
      "sentiment_label": "Neutral",
      "bullish_pct": null,
      "tweet_volume": 223346,
      "price": 1.49,
      "change_pct": "+103.62%",
      "key_topics": [
        "Momentum",
        "Volume Spike"
      ]
    },
    {
      "ticker": "ZBRA",
      "name": "Zebra Technologies Corporation",
      "sentiment_delta": 0.0,
      "current_sentiment": 0.0,
      "sentiment_label": "Neutral",
      "bullish_pct": null,
      "tweet_volume": 2978,
      "price": 254.09,
      "change_pct": "+17.11%",
      "key_topics": [
        "Momentum",
        "Volume Spike"
      ]
    },
    {
      "ticker": "ERNA",
      "name": "Ernexa Therapeutics Inc.",
      "sentiment_delta": 0.0,
      "current_sentiment": 0.0,
      "sentiment_label": "Neutral",
      "bullish_pct": null,
      "tweet_volume": 34158,
      "price": 13.07,
      "change_pct": "+81.28%",
      "key_topics": [
        "Momentum",
        "Volume Spike"
      ]
    },
    {
      "ticker": "SE",
      "name": "Sea Limited",
      "sentiment_delta": 0.0,
      "current_sentiment": 0.0,
      "sentiment_label": "Neutral",
      "bullish_pct": null,
      "tweet_volume": 20044,
      "price": 94.5,
      "change_pct": "+11.35%",
      "key_topics": [
        "Momentum",
        "Volume Spike"
      ]
    },
    {
      "ticker": "ONON",
      "name": "On Holding AG",
      "sentiment_delta": 0.0,
      "current_sentiment": 0.0,
      "sentiment_label": "Neutral",
      "bullish_pct": null,
      "tweet_volume": 20751,
      "price": 32.22,
      "change_pct": "-5.36%",
      "key_topics": [
        "Momentum",
        "Volume Spike"
      ]
    },
    {
      "ticker": "GME",
      "name": "GameStop Corporation",
      "sentiment_delta": 0.0,
      "current_sentiment": 0.0,
      "sentiment_label": "Neutral",
      "bullish_pct": null,
      "tweet_volume": 13432,
      "price": 22.81,
      "change_pct": "-1.55%",
      "key_topics": [
        "Momentum",
        "Volume Spike"
      ]
    },
    {
      "ticker": "PSIX",
      "name": "Power Solutions International, ",
      "sentiment_delta": 0.0,
      "current_sentiment": 0.0,
      "sentiment_label": "Neutral",
      "bullish_pct": null,
      "tweet_volume": 7754,
      "price": 39.01,
      "change_pct": "-37.53%",
      "key_topics": [
        "Momentum",
        "Volume Spike"
      ]
    },
    {
      "ticker": "PACS",
      "name": "PACS Group, Inc.",
      "sentiment_delta": 0.0,
      "current_sentiment": 0.0,
      "sentiment_label": "Neutral",
      "bullish_pct": null,
      "tweet_volume": 3709,
      "price": 38.94,
      "change_pct": "+22.07%",
      "key_topics": [
        "Momentum",
        "Volume Spike"
      ]
    },
    {
      "ticker": "VG",
      "name": "Venture Global, Inc.",
      "sentiment_delta": 0.0,
      "current_sentiment": 0.0,
      "sentiment_label": "Neutral",
      "bullish_pct": null,
      "tweet_volume": 38860,
      "price": 13.04,
      "change_pct": "+12.18%",
      "key_topics": [
        "Momentum",
        "Volume Spike"
      ]
    },
    {
      "ticker": "UA",
      "name": "Under Armour, Inc.",
      "sentiment_delta": 0.0,
      "current_sentiment": 0.0,
      "sentiment_label": "Neutral",
      "bullish_pct": null,
      "tweet_volume": 11006,
      "price": 4.83,
      "change_pct": "-17.94%",
      "key_topics": [
        "Momentum",
        "Volume Spike"
      ]
    }
  ]
}