{
  "updated_at": "2026-04-10T14:16:31.679189+00:00",
  "top_trending": {
    "ticker": "SNOW",
    "name": "Snowflake Inc.",
    "sentiment_delta": 0.0,
    "current_sentiment": 0.0,
    "tweet_volume": 12378,
    "price": 124.25,
    "change_pct": "-6.04%",
    "key_topics": [
      "Momentum",
      "Volume Spike"
    ]
  },
  "trending_list": [
    {
      "ticker": "TEM",
      "name": "Tempus AI, Inc.",
      "sentiment_delta": 0.0,
      "current_sentiment": 0.0,
      "tweet_volume": 2783,
      "price": 44.98,
      "change_pct": "+1.85%",
      "key_topics": [
        "Momentum",
        "Volume Spike"
      ]
    },
    {
      "ticker": "NOW",
      "name": "ServiceNow, Inc.",
      "sentiment_delta": 0.0,
      "current_sentiment": 0.0,
      "tweet_volume": 35006,
      "price": 84.28,
      "change_pct": "-6.15%",
      "key_topics": [
        "Momentum",
        "Volume Spike"
      ]
    },
    {
      "ticker": "EOSE",
      "name": "Eos Energy Enterprises, Inc.",
      "sentiment_delta": 0.0,
      "current_sentiment": 0.0,
      "tweet_volume": 46160,
      "price": 6.08,
      "change_pct": "+2.27%",
      "key_topics": [
        "Momentum",
        "Volume Spike"
      ]
    },
    {
      "ticker": "DKNG",
      "name": "DraftKings Inc.",
      "sentiment_delta": 0.0,
      "current_sentiment": 0.0,
      "tweet_volume": 3344,
      "price": 22.41,
      "change_pct": "+0.74%",
      "key_topics": [
        "Momentum",
        "Volume Spike"
      ]
    },
    {
      "ticker": "OGN",
      "name": "Organon & Co.",
      "sentiment_delta": 0.0,
      "current_sentiment": 0.0,
      "tweet_volume": 38553,
      "price": 8.64,
      "change_pct": "+25.11%",
      "key_topics": [
        "Momentum",
        "Volume Spike"
      ]
    },
    {
      "ticker": "RAYA",
      "name": "Erayak Power Solution Group Inc",
      "sentiment_delta": 0.0,
      "current_sentiment": 0.0,
      "tweet_volume": 406498,
      "price": 0.75,
      "change_pct": "+64.11%",
      "key_topics": [
        "Momentum",
        "Volume Spike"
      ]
    },
    {
      "ticker": "NET",
      "name": "Cloudflare, Inc.",
      "sentiment_delta": 0.0,
      "current_sentiment": 0.0,
      "tweet_volume": 8536,
      "price": 170.5,
      "change_pct": "-11.68%",
      "key_topics": [
        "Momentum",
        "Volume Spike"
      ]
    },
    {
      "ticker": "ISPC",
      "name": "iSpecimen Inc.",
      "sentiment_delta": 0.0,
      "current_sentiment": 0.0,
      "tweet_volume": 710083,
      "price": 0.17,
      "change_pct": "+32.28%",
      "key_topics": [
        "Momentum",
        "Volume Spike"
      ]
    },
    {
      "ticker": "OKTA",
      "name": "Okta, Inc.",
      "sentiment_delta": 0.0,
      "current_sentiment": 0.0,
      "tweet_volume": 1784,
      "price": 65.43,
      "change_pct": "-3.44%",
      "key_topics": [
        "Momentum",
        "Volume Spike"
      ]
    },
    {
      "ticker": "CREG",
      "name": "Smart Powerr Corp.",
      "sentiment_delta": 0.0,
      "current_sentiment": 0.0,
      "tweet_volume": 582212,
      "price": 0.91,
      "change_pct": "+167.62%",
      "key_topics": [
        "Momentum",
        "Volume Spike"
      ]
    }
  ]
}